octo_pipeline_python/backends/pipenv/__init__.py
octo_pipeline_python/backends/pipenv/pipenv_backend.py
octo_pipeline_python/backends/pipenv/actions/__init__.py
octo_pipeline_python/backends/pipenv/actions/pipenv_activate.py
octo_pipeline_python/backends/pipenv/actions/pipenv_consume.py
octo_pipeline_python/backends/pipenv/actions/pipenv_execute.py
octo_pipeline_python/backends/pipenv/models/__init__.py
octo_pipeline_python/backends/pipenv/models/pipenv_model.py
octo_pipeline_backend_pipenv_python-1.3.2.dist-info/LICENSE.txt
octo_pipeline_backend_pipenv_python-1.3.2.dist-info/METADATA
octo_pipeline_backend_pipenv_python-1.3.2.dist-info/README.md
octo_pipeline_backend_pipenv_python-1.3.2.dist-info/WHEEL
octo_pipeline_backend_pipenv_python-1.3.2.dist-info/top_level.txt
octo_pipeline_backend_pipenv_python-1.3.2.dist-info/RECORD
